cryptocoreedu/__init__.py
cryptocoreedu/cli_parser.py
cryptocoreedu/csprng.py
cryptocoreedu/exceptions.py
cryptocoreedu/file_io.py
cryptocoreedu/main.py
cryptocoreedu/docs/__init__.py
cryptocoreedu/hash/__init__.py
cryptocoreedu/hash/sha256.py
cryptocoreedu/hash/sha3_256.py
cryptocoreedu/kdf/__init__.py
cryptocoreedu/kdf/hkdf.py
cryptocoreedu/kdf/pbkdf2.py
cryptocoreedu/mac/__init__.py
cryptocoreedu/mac/hmac.py
cryptocoreedu/modes/CBCMode.py
cryptocoreedu/modes/CFBMode.py
cryptocoreedu/modes/CTRMode.py
cryptocoreedu/modes/ECBMode.py
cryptocoreedu/modes/ETMMode.py
cryptocoreedu/modes/GCMMode.py
cryptocoreedu/modes/OFBMode.py
cryptocoreedu/modes/__init__.py
cryptocoreedu/utils/__init__.py
cryptocoreedu/utils/padding.py
cryptocoreedu/utils/validators.py
tests/__init__.py
tests/test_openssl.py
tests/integration/__init__.py
tests/integration/test_cli_parser.py
tests/unit/__init__.py
tests/unit/test_cbc_mode.py
tests/unit/test_cfb_mode.py
tests/unit/test_csprng.py
tests/unit/test_ctr_mode.py
tests/unit/test_ecb_mode.py
tests/unit/test_etm_mode.py
tests/unit/test_gcm_mode.py
tests/unit/test_hkdf.py
tests/unit/test_hmac.py
tests/unit/test_ofb_mode.py
tests/unit/test_pbkdf2.py
tests/unit/test_sha256.py
tests/unit/test_sha3_256.py
cryptocoreedu-2.0.0.dist-info/METADATA
cryptocoreedu-2.0.0.dist-info/WHEEL
cryptocoreedu-2.0.0.dist-info/entry_points.txt
cryptocoreedu-2.0.0.dist-info/top_level.txt
cryptocoreedu-2.0.0.dist-info/RECORD
