Metadata-Version: 2.4
Name: cryptocoreedu
Version: 2.0.0
Summary: Educational cryptography toolkit
Author: michaans
Keywords: cryptography,educational,aes,ecb
Requires-Python: >=3.8
Requires-Dist: pycryptodome>=3.23.0
Dynamic: author
Dynamic: description
Dynamic: description-content-type
Dynamic: keywords
Dynamic: requires-dist
Dynamic: requires-python
Dynamic: summary
